red_string_grouper
