Metadata-Version: 2.1
Name: red-string-grouper
Version: 0.0.3
Summary: Row Equivalence Discoverer (red) based on string_grouper. This package finds similarities between rows of a table.
Home-page: https://github.com/ParticularMiner/red_string_grouper
Author: Particular Miner
Author-email: particularminer@fake.com
License: MIT
Download-URL: https://github.com/ParticularMiner/red_string_grouper/archive/refs/tags/v0.0.3.tar.gz
Keywords: record-linkage cosine-similarity tf-idf string_grouper sparse_dot_topn python cython
Platform: UNKNOWN
